open_deepsearch/__init__.py
open_deepsearch/deep_research.py
open_deepsearch/feedback.py
open_deepsearch/main.py
open_deepsearch/output_manager.py
open_deepsearch/progress_manager.py
open_deepsearch/prompt.py
open_deepsearch/research_progress_results.py
open_deepsearch/run.py
open_deepsearch/test_crawler.py
open_deepsearch/ai/__init__.py
open_deepsearch/ai/providers.py
open_deepsearch/ai/text_splitter.py
open_deepsearch/ai/text_splitter_test.py
open_deepsearch-0.1.6.dist-info/LICENSE
open_deepsearch-0.1.6.dist-info/METADATA
open_deepsearch-0.1.6.dist-info/WHEEL
open_deepsearch-0.1.6.dist-info/entry_points.txt
open_deepsearch-0.1.6.dist-info/top_level.txt
open_deepsearch-0.1.6.dist-info/RECORD
